bovaqulov/__init__.py
bovaqulov/social.py
bovaqulov-0.1.0.dist-info/METADATA
bovaqulov-0.1.0.dist-info/WHEEL
bovaqulov-0.1.0.dist-info/RECORD
